xia_git/__init__.py
xia_git/git.cpython-311-darwin.so
xia_git-0.1.6.dist-info/LICENSE.txt
xia_git-0.1.6.dist-info/METADATA
xia_git-0.1.6.dist-info/WHEEL
xia_git-0.1.6.dist-info/top_level.txt
xia_git-0.1.6.dist-info/RECORD
