Metadata-Version: 2.1
Name: xia-git
Version: 0.1.6
Home-page: https://develop.x-i-a.com/docs/xia-git/0.1.6/index.html
Author: X-I-A
Author-email: admin@x-i-a.com
Requires-Python: >=3.9
License-File: LICENSE.txt
Requires-Dist: GitPython
